clearblade_cloud_iot-2.0.7-nspkg.pth
clearblade/cloud/iot_v1/__init__.py
clearblade/cloud/iot_v1/client.py
clearblade/cloud/iot_v1/config.py
clearblade/cloud/iot_v1/config_manager.py
clearblade/cloud/iot_v1/developer_tests.py
clearblade/cloud/iot_v1/device_types.py
clearblade/cloud/iot_v1/devices.py
clearblade/cloud/iot_v1/http_client.py
clearblade/cloud/iot_v1/pagers.py
clearblade/cloud/iot_v1/registry.py
clearblade/cloud/iot_v1/registry_types.py
clearblade/cloud/iot_v1/resources.py
clearblade/cloud/iot_v1/utils.py
clearblade_cloud_iot-2.0.7.dist-info/LICENSE
clearblade_cloud_iot-2.0.7.dist-info/METADATA
clearblade_cloud_iot-2.0.7.dist-info/WHEEL
clearblade_cloud_iot-2.0.7.dist-info/namespace_packages.txt
clearblade_cloud_iot-2.0.7.dist-info/top_level.txt
clearblade_cloud_iot-2.0.7.dist-info/RECORD
